nyaascraper/__init__.py
nyaascraper/_version.py
nyaascraper/client.py
nyaascraper/exceptions.py
nyaascraper/models.py
nyaascraper/rss.py
nyaascraper/enums/__init__.py
nyaascraper/enums/categories.py
nyaascraper/enums/quality_filter.py
nyaascraper/enums/site.py
nyaascraper/enums/sorting.py
nyaascraper/enums/torrent_filter.py
nyaascraper/enums/torrent_type.py
nyaascraper/enums/user_level.py
nyaasi_scraper-3.0.1.dist-info/METADATA
nyaasi_scraper-3.0.1.dist-info/WHEEL
nyaasi_scraper-3.0.1.dist-info/top_level.txt
nyaasi_scraper-3.0.1.dist-info/RECORD
