Metadata-Version: 2.1
Name: nyaasi-scraper
Version: 3.0.1
Summary: nyaasi-scraper is an asynchronous Python library for scraping nyaa.si and sukebei.nyaa.si.
Home-page: https://github.com/zrekryu/nyaasi-scraper
Author: ZrekryuDev
Author-email: zrekryudev@gmail.com
Keywords: nyaa,sukebei,torrent,asynchronous,web scraping
Classifier: Development Status :: 5 - Production/Stable
Classifier: Intended Audience :: Developers
Classifier: License :: OSI Approved :: MIT License
Classifier: Operating System :: OS Independent
Classifier: Programming Language :: Python
Classifier: Programming Language :: Python :: 3
Classifier: Topic :: Internet :: WWW/HTTP :: Indexing/Search
Classifier: Topic :: Software Development :: Libraries
Requires-Dist: h
Requires-Dist: t
Requires-Dist: p
Requires-Dist: x
Requires-Dist: b
Requires-Dist: e
Requires-Dist: a
Requires-Dist: u
Requires-Dist: i
Requires-Dist: f
Requires-Dist: l
Requires-Dist: s
Requires-Dist: o
Requires-Dist: 4
Requires-Dist: d
Requires-Dist: r
